FastDataMask/.___init__.py
FastDataMask/__init__.py
FastDataMask/clsCircularList.py
fastdatamask-0.0.6.dist-info/METADATA
fastdatamask-0.0.6.dist-info/WHEEL
fastdatamask-0.0.6.dist-info/RECORD
