Metadata-Version: 2.1
Name: FastDataMask
Version: 0.0.6
Summary: This is the main class that will generate masked data for light weight use cases.
Project-URL: Homepage, https://github.com/SatyakiDe2019/FastDataMask
Project-URL: Bug Tracker, https://github.com/SatyakiDe2019/FastDataMask/issues
Author-email: Satyaki De <satyakide.us@gmail.com>
License: Copyright 2023 @ Satyaki De
Classifier: License :: OSI Approved :: MIT License
Classifier: Operating System :: OS Independent
Classifier: Programming Language :: Python :: 3
Requires-Python: >=3.7
